LICENSE
monitor_commander/__init__.py
monitor_commander/monitor_commander.py
monitor_commander-0.2.0.dist-info/entry_points.txt
monitor_commander-0.2.0.dist-info/LICENSE
monitor_commander-0.2.0.dist-info/WHEEL
monitor_commander-0.2.0.dist-info/METADATA
monitor_commander-0.2.0.dist-info/RECORD
