Metadata-Version: 2.1
Name: monitor-commander
Version: 0.2.0
Summary: Control your monitors using ddc/ci
Home-page: https://gitlab.com/vmeurisse/monitor-commander
License: MIT
Keywords: monitor,ddc,ddc/ci,vcp
Author: Vincent Meurisse
Author-email: dev@meurisse.org
Requires-Python: >=3.8,<4.0
Classifier: Environment :: Console
Classifier: License :: OSI Approved :: MIT License
Classifier: Operating System :: POSIX :: Linux
Classifier: Programming Language :: Python :: 3
Classifier: Programming Language :: Python :: 3.10
Classifier: Programming Language :: Python :: 3.8
Classifier: Programming Language :: Python :: 3.9
Classifier: Topic :: Desktop Environment
Classifier: Topic :: Home Automation
Classifier: Topic :: Other/Nonlisted Topic
Classifier: Topic :: System :: Hardware
Classifier: Topic :: Utilities
Requires-Dist: PyYAML (>=6.0,<7.0)
Requires-Dist: argcomplete (>=2.0.0,<3.0.0)
Requires-Dist: typedload (>=2.12,<3.0)
Project-URL: Repository, https://gitlab.com/vmeurisse/monitor-commander
